pyeodh/__init__.py
pyeodh/ades.py
pyeodh/client.py
pyeodh/consts.py
pyeodh/eodh_object.py
pyeodh/pagination.py
pyeodh/py.typed
pyeodh/resource_catalog.py
pyeodh/types.py
pyeodh/utils.py
pyeodh/workspace.py
pyeodh-0.1.7.dist-info/METADATA
pyeodh-0.1.7.dist-info/WHEEL
pyeodh-0.1.7.dist-info/licenses/LICENSE
pyeodh-0.1.7.dist-info/RECORD
