Metadata-Version: 2.4
Name: pyeodh
Version: 0.1.7
Summary: A lightweight Python client for EODH APIs.
License: BSD-3-Clause
License-File: LICENSE
Author: Dusan Figala
Author-email: dusan@oxidian.com
Requires-Python: >=3.9,<4.0
Classifier: License :: OSI Approved :: BSD License
Classifier: Programming Language :: Python :: 3
Classifier: Programming Language :: Python :: 3.9
Classifier: Programming Language :: Python :: 3.10
Classifier: Programming Language :: Python :: 3.11
Classifier: Programming Language :: Python :: 3.12
Classifier: Programming Language :: Python :: 3.13
Classifier: Programming Language :: Python :: 3.14
Requires-Dist: ceda-datapoint (>=0.4.12,<0.5.0)
Requires-Dist: lxml (==5.3.0)
Requires-Dist: owslib (>=0.31.0,<0.32.0)
Requires-Dist: poetry (>=1.8.5,<2.0.0)
Requires-Dist: pystac (>=1.10.0,<2.0.0)
Requires-Dist: requests-oauthlib (>=2.0.0,<3.0.0)
Requires-Dist: zarr (>=2,<3)
